avro_byte_counter/__init__.py
avro_byte_counter/avro_byte_counter.py
avro_byte_counter/type.py
avro_byte_counter/utils.py
avro_byte_counter-0.1.0.dist-info/METADATA
avro_byte_counter-0.1.0.dist-info/WHEEL
avro_byte_counter-0.1.0.dist-info/RECORD
