Metadata-Version: 2.1
Name: avro-byte-counter
Version: 0.1.0
Summary: Count number of bytes per field
License: MIT
Author: Louis Fruleux
Author-email: louis.fruleux1@gmail.com
Requires-Python: >=3.8
Classifier: License :: OSI Approved :: MIT License
Classifier: Programming Language :: Python :: 3
Classifier: Programming Language :: Python :: 3.8
Classifier: Programming Language :: Python :: 3.9
Classifier: Programming Language :: Python :: 3.10
Classifier: Programming Language :: Python :: 3.11
Requires-Dist: avro (>=1.11.1,<2.0.0)
